FRion/correct.py
FRion/download_IONEX_CDDIS.py
FRion/predict.py
FRion-1.1.5.dist-info/LICENSE
FRion-1.1.5.dist-info/METADATA
FRion-1.1.5.dist-info/WHEEL
FRion-1.1.5.dist-info/entry_points.txt
FRion-1.1.5.dist-info/top_level.txt
FRion-1.1.5.dist-info/RECORD
