Metadata-Version: 2.1
Name: FRion
Version: 1.1.5
Summary: Ionospheric Faraday rotation prediction and correction for radio astronomy polarization cubes.
Home-page: https://github.com/Cameron-Van-Eck/FRion
Download-URL: https://github.com/Cameron-Van-Eck/FRion/archive/refs/heads/main.zip
Maintainer: Cameron Van Eck
Maintainer-email: cameron.vaneck@anu.edu.au
License: MIT
Classifier: Development Status :: 5 - Production/Stable
Classifier: License :: OSI Approved :: MIT License
Classifier: Programming Language :: Python
Classifier: Programming Language :: Python :: 3
Classifier: Programming Language :: Python :: 3.5
Classifier: Intended Audience :: Science/Research
Classifier: Topic :: Scientific/Engineering :: Astronomy
Requires-Python: >=3.5.0
License-File: LICENSE
Requires-Dist: numpy
Requires-Dist: astropy
Requires-Dist: pyephem
Requires-Dist: requests
Requires-Dist: scipy
